trinary_tree/__init__.py
trinary_tree/binary_tree.py
trinary_tree/cv_test_pipeline.py
trinary_tree/trinary_mia_tree.py
trinary_tree/trinary_tree.py
trinary_tree/weighted_tree.py
trinary_tree-0.1.23.dist-info/LICENSE
trinary_tree-0.1.23.dist-info/METADATA
trinary_tree-0.1.23.dist-info/WHEEL
trinary_tree-0.1.23.dist-info/top_level.txt
trinary_tree-0.1.23.dist-info/RECORD
