Metadata-Version: 2.1
Name: trinary-tree
Version: 0.1.23
Summary: Python package for the Trinary Tree algorithm
Home-page: https://github.com/henningz/trinary-tree
Author: Henning Zakrisson
Author-email: henning.zakrisson@gmail.com
Classifier: Programming Language :: Python :: 3
Classifier: License :: OSI Approved :: MIT License
Classifier: Operating System :: OS Independent
Requires-Python: >=3.6
License-File: LICENSE
Requires-Dist: numpy ==1.24.3
Requires-Dist: pandas ==2.0.2
Requires-Dist: scikit-learn ==1.2.2
